odoo/addons/base_ubl_generate/README.rst
odoo/addons/base_ubl_generate/__init__.py
odoo/addons/base_ubl_generate/__manifest__.py
odoo/addons/base_ubl_generate/i18n/base_ubl.pot
odoo/addons/base_ubl_generate/i18n/base_ubl_generate.pot
odoo/addons/base_ubl_generate/i18n/es.po
odoo/addons/base_ubl_generate/i18n/fr.po
odoo/addons/base_ubl_generate/i18n/hr.po
odoo/addons/base_ubl_generate/i18n/it.po
odoo/addons/base_ubl_generate/i18n/nl.po
odoo/addons/base_ubl_generate/models/__init__.py
odoo/addons/base_ubl_generate/models/ubl.py
odoo/addons/base_ubl_generate/readme/CONTRIBUTORS.md
odoo/addons/base_ubl_generate/readme/DESCRIPTION.md
odoo/addons/base_ubl_generate/static/description/icon.png
odoo/addons/base_ubl_generate/static/description/index.html
odoo/addons/base_ubl_generate/tests/__init__.py
odoo/addons/base_ubl_generate/tests/common.py
odoo/addons/base_ubl_generate/tests/test_ubl_generate_base.py
odoo/addons/base_ubl_generate/tests/test_ubl_generate_invoice.py
odoo_addon_base_ubl_generate-18.0.1.0.0.4.dist-info/METADATA
odoo_addon_base_ubl_generate-18.0.1.0.0.4.dist-info/WHEEL
odoo_addon_base_ubl_generate-18.0.1.0.0.4.dist-info/top_level.txt
odoo_addon_base_ubl_generate-18.0.1.0.0.4.dist-info/RECORD
